{
  "id": "a2c9e90c-4bec-874f-a55b-14c295dac154",
  "offset": "2333",
  "occurred": "2015-11-13T17:10:44.393Z",
  "processed": "2015-11-13T17:10:44.393Z",
  "device": {
    "amazon_channel": "6c1124fc-d52b-9b00-ef14-98d9ceaa9888"
  },
  "body": {
    "add": {
      "device": [
        "graphic_tees"
      ]
    },
    "current": {
      "device": [
        "graphic_tees",
        "dress_shirts",
        "omg_shoes",
        "dad_jeans",
        "sombreros"
      ]
    }
  },
  "type": "TAG_CHANGE"
}