{
  "id": "c46da6dd-2541-4df1-1745-2509a021137b",
  "offset": "850",
  "occurred": "2015-11-13T16:46:01.394Z",
  "processed": "2015-11-13T16:46:01.394Z",
  "device": {
    "ios_channel": "d0866a65-5a87-ea1e-b0b0-1b35259388fe"
  },
  "body": {
    "add": {
      "device": [
        "dad_jeans"
      ]
    },
    "current": {
      "device": [
        "dad_jeans",
        "high_heels",
        "that_one_ratty_tshirt",
        "swimsuits",
        "bow_ties"
      ]
    }
  },
  "type": "TAG_CHANGE"
}