{
  "id": "00fd2cd7-4f60-39fe-b18e-16b9037cc860",
  "offset": "2162",
  "occurred": "2015-11-13T17:07:53.393Z",
  "processed": "2015-11-13T17:07:53.393Z",
  "device": {
    "amazon_channel": "9e8abb40-2261-6028-bceb-2a292d1ca195"
  },
  "body": {
    "add": {
      "device": [
        "cowboy_boots"
      ]
    },
    "current": {
      "device": [
        "cowboy_boots",
        "turtlenecks",
        "startup_tees",
        "sombreros",
        "that_one_ratty_tshirt"
      ]
    }
  },
  "type": "TAG_CHANGE"
}