{
  "id": "8e1ad397-8eb4-9723-5efa-d8f8c60fc269",
  "offset": "1852",
  "occurred": "2015-11-13T17:02:43.393Z",
  "processed": "2015-11-13T17:02:43.393Z",
  "device": {
    "android_channel": "9b3e2500-849a-99c7-bc4e-ca8149f2be86"
  },
  "body": {
    "add": {
      "device": [
        "sombreros"
      ]
    },
    "current": {
      "device": [
        "sombreros",
        "suspenders",
        "that_one_ratty_tshirt",
        "swimsuits",
        "omg_shoes"
      ]
    }
  },
  "type": "TAG_CHANGE"
}