{
  "id": "3450804f-9596-7aa5-44db-16db2a2060ea",
  "offset": "1930",
  "occurred": "2015-11-13T17:04:01.394Z",
  "processed": "2015-11-13T17:04:01.394Z",
  "device": {
    "android_channel": "e10e0302-c762-759e-418c-4034e6545883"
  },
  "body": {
    "add": {
      "device": [
        "turtlenecks"
      ]
    },
    "current": {
      "device": [
        "turtlenecks",
        "bow_ties",
        "dad_jeans",
        "cowboy_boots",
        "raincoats"
      ]
    }
  },
  "type": "TAG_CHANGE"
}